flywheel_gear_cli/__init__.py
flywheel_gear_cli/gear/__init__.py
flywheel_gear_cli/gear/gear_build.py
flywheel_gear_cli/gear/gear_config.py
flywheel_gear_cli/gear/gear_run.py
flywheel_gear_cli/gear/gear_update_env.py
flywheel_gear_cli/gear/gear_upload.py
flywheel_gear_cli/gear/gear_validate_manifest.py
flywheel_gear_cli/gear/gears.py
flywheel_gear_cli/gear_cli.py
flywheel_gear_cli/job/__init__.py
flywheel_gear_cli/job/job_pull.py
flywheel_gear_cli/job/jobs.py
flywheel_gear_cli/logging.py
flywheel_gear_cli/utils.py
flywheel_gear_cli-0.1.0a7.dist-info/entry_points.txt
flywheel_gear_cli-0.1.0a7.dist-info/LICENSE
flywheel_gear_cli-0.1.0a7.dist-info/WHEEL
flywheel_gear_cli-0.1.0a7.dist-info/METADATA
flywheel_gear_cli-0.1.0a7.dist-info/RECORD
