Metadata-Version: 2.1
Name: flywheel-gear-cli
Version: 0.1.0a7
Summary: CLI for gear operations
License: MIT
Author: Flywheel
Author-email: support@flywheel.io
Requires-Python: >=3.8,<4.0
Classifier: License :: OSI Approved :: MIT License
Classifier: Programming Language :: Python :: 3
Classifier: Programming Language :: Python :: 3.8
Classifier: Programming Language :: Python :: 3.9
Requires-Dist: colorama (>=0.4.4,<0.5.0)
Requires-Dist: docker (>=5.0.0,<6.0.0)
Requires-Dist: flywheel-gear-toolkit (>=0.3.2,<0.4.0)
Requires-Dist: humanize (>=3.9.0,<4.0.0)
Requires-Dist: pydantic (>=1.8.2,<2.0.0)
